client/__init__.py
client/main.py
client/classes/CustomTqdm.py
client/classes/DatasetManager.py
client/classes/__init__.py
client/utils/__init__.py
client/utils/login.py
client/utils/utils.py
client/utils/cmd_utils/__init__.py
client/utils/cmd_utils/cmd_doc.py
client/utils/cmd_utils/cmd_fdr.py
client/utils/cmd_utils/cmd_logs.py
client/utils/cmd_utils/cmd_main.py
client/utils/dvc_utils/__init__.py
client/utils/dvc_utils/dvc_ops.py
client/utils/dvc_utils/dvc_venv.py
fdr_dev5-0.1.0.dist-info/METADATA
fdr_dev5-0.1.0.dist-info/WHEEL
fdr_dev5-0.1.0.dist-info/entry_points.txt
fdr_dev5-0.1.0.dist-info/top_level.txt
fdr_dev5-0.1.0.dist-info/RECORD
