Metadata-Version: 2.1
Name: fdr-dev5
Version: 0.1.0
Summary: Sample fdr lib
Author: Konstantinos Gyftodimos
Author-email: konstgyftodimos@gmail.com
